foo_cv/__init__.py
foo_cv/cli.py
foo_cv/utils.py
foo_cv-0.2.3.dist-info/LICENSE
foo_cv-0.2.3.dist-info/METADATA
foo_cv-0.2.3.dist-info/WHEEL
foo_cv-0.2.3.dist-info/entry_points.txt
foo_cv-0.2.3.dist-info/RECORD
